multipurposediscord/__init__.py
multipurpose_discord-0.0.1.dist-info/LICENSE
multipurpose_discord-0.0.1.dist-info/METADATA
multipurpose_discord-0.0.1.dist-info/WHEEL
multipurpose_discord-0.0.1.dist-info/top_level.txt
multipurpose_discord-0.0.1.dist-info/RECORD
