Metadata-Version: 2.1
Name: multipurpose-discord
Version: 0.0.1
Summary: A package made for multipurpose stuff!
Home-page: UNKNOWN
Author: MrPotato
License: MIT
Keywords: discord.py,discord,discord-multipurpose
Platform: UNKNOWN
Requires-Python: >=3.5.3
License-File: LICENSE
